xso/__init__.py
xso/backendcomps.py
xso/component.py
xso/core.py
xso/model.py
xso/solvers.py
xso/variables.py
xso/xsimlabwrappers.py
xso-0.1.0.dist-info/LICENSE
xso-0.1.0.dist-info/METADATA
xso-0.1.0.dist-info/WHEEL
xso-0.1.0.dist-info/RECORD
