Metadata-Version: 2.1
Name: xso
Version: 0.1.0
Summary: Framework for building and solving ODE-based models, an extension of xarray-simlab
License: BSD 3-Clause
Author: Benjamin Post
Requires-Python: >=3.8,<4.0
Classifier: License :: Other/Proprietary License
Classifier: Programming Language :: Python :: 3
Classifier: Programming Language :: Python :: 3.8
Classifier: Programming Language :: Python :: 3.9
Classifier: Programming Language :: Python :: 3.10
Classifier: Programming Language :: Python :: 3.11
Requires-Dist: dask[distributed] (>=2022.10.0)
Requires-Dist: numpy
Requires-Dist: scipy (>=1.9.1)
Requires-Dist: tqdm
Requires-Dist: xarray (>=0.10.0)
Requires-Dist: xarray-simlab (>=0.5.0,<0.6.0)
Requires-Dist: zarr (>=2.3.0)
